paraplume/__init__.py
paraplume/build_dictionary.py
paraplume/create_embeddings.py
paraplume/infer.py
paraplume/predict.py
paraplume/shapp_utils.py
paraplume/torch_dataset.py
paraplume/train.py
paraplume/utils.py
paraplume/background/ablang2_heavy.pt
paraplume/background/ablang2_light.pt
paraplume/background/antiberty_heavy.pt
paraplume/background/antiberty_light.pt
paraplume/background/esm_heavy.pt
paraplume/background/esm_light.pt
paraplume/background/igT5_heavy.pt
paraplume/background/igT5_light.pt
paraplume/background/igbert_heavy.pt
paraplume/background/igbert_light.pt
paraplume/background/prot-t5_heavy.pt
paraplume/background/prot-t5_light.pt
paraplume/trained_models/large_1_0/checkpoint.pt
paraplume/trained_models/large_1_0/summary_dict.json
paraplume/trained_models/small_1_0/checkpoint.pt
paraplume/trained_models/small_1_0/summary_dict.json
paraplume-1.1.1.dist-info/licenses/LICENCE
paraplume-1.1.1.dist-info/METADATA
paraplume-1.1.1.dist-info/WHEEL
paraplume-1.1.1.dist-info/entry_points.txt
paraplume-1.1.1.dist-info/top_level.txt
paraplume-1.1.1.dist-info/RECORD
