Metadata-Version: 2.4
Name: paraplume
Version: 1.1.1
Author-email: Gabriel Athènes <gabriel.athenes@polytechnique.edu>
Maintainer-email: Gabriel Athènes <gabriel.athenes@polytechnique.edu>
Classifier: Development Status :: 3 - Alpha
Classifier: Intended Audience :: Developers
Classifier: Intended Audience :: Healthcare Industry
Classifier: Intended Audience :: Science/Research
Classifier: Topic :: Scientific/Engineering :: Bio-Informatics
Classifier: Topic :: Scientific/Engineering :: Physics
Classifier: Topic :: Scientific/Engineering :: Medical Science Apps.
Classifier: License :: Other/Proprietary License
Classifier: Natural Language :: English
Classifier: Programming Language :: Python :: 3.10
Classifier: Programming Language :: Python :: 3.11
Classifier: Programming Language :: Python :: 3.12
Requires-Python: >=3.10
License-File: LICENCE
Requires-Dist: ablang2<1,>=0.2.1
Requires-Dist: antiberty<1,>=0.1.3
Requires-Dist: numpy<3,>=1.23.5
Requires-Dist: pandas<3,>=2.2
Requires-Dist: structlog<25,>=24.0.0
Requires-Dist: tqdm<5,>=4.66
Requires-Dist: typer<1,>=0.9
Requires-Dist: torch<3,>=2.5.0
Requires-Dist: fair-esm<3,>=2.0.0
Requires-Dist: matplotlib<4,>=3.9.2
Requires-Dist: biopandas<1,>=0.5.1
Requires-Dist: scikit-learn<2,>=1.5.2
Requires-Dist: sentencepiece<1,>=0.2.0
Requires-Dist: shap<1
Dynamic: license-file
